{"config": {"view": {"width": 400, "height": 300}, "mark": {"tooltip": null}}, "hconcat": [{"layer": [{"mark": "point", "encoding": {"color": {"condition": {"type": "nominal", "field": "bez_y", "legend": null, "selection": "selector579"}, "value": "lightgray"}, "tooltip": [{"type": "temporal", "field": "datum", "title": "Datum"}, {"type": "nominal", "field": "knoten", "title": "OrtsID"}, {"type": "nominal", "field": "bez_x", "title": "Ort"}, {"type": "quantitative", "field": "hour_counts_bike", "title": "st\u00fcndl. Anzahl von Radf"}, {"type": "quantitative", "field": "Radanteil", "format": ".1%", "title": "Radanteil"}], "x": {"type": "quantitative", "axis": {"format": "0", "title": "Jahr"}, "field": "year", "scale": {"zero": false}}, "y": {"type": "quantitative", "axis": {"format": "%", "title": "Radanteil"}, "field": "Radanteil"}}, "title": "10997"}, {"mark": {"type": "line", "size": 1}, "encoding": {"color": {"condition": {"type": "nominal", "field": "bez_y", "legend": null, "selection": "selector579"}, "value": "lightgray"}, "x": {"type": "quantitative", "field": "year"}, "y": {"type": "quantitative", "field": "Radanteil"}}, "transform": [{"filter": {"selection": "selector579"}}]}, {"data": {"name": "data-397ee10584af86895d2bb8ae89964b56"}, "mark": {"type": "line", "strokeDash": [10, 10]}, "encoding": {"color": {"condition": {"type": "nominal", "field": "bez_y", "legend": null, "selection": "selector579"}, "value": "lightgray"}, "tooltip": [{"type": "nominal", "field": "bez_y"}], "x": {"type": "quantitative", "field": "xfit"}, "y": {"type": "quantitative", "field": "yfit"}}, "transform": [{"filter": {"selection": "selector579"}}]}]}, {"mark": "point", "encoding": {"color": {"condition": {"type": "nominal", "field": "bez_y", "legend": null, "selection": "selector579"}, "value": "lightgray"}, "tooltip": {"type": "nominal", "field": "bez_y"}, "y": {"type": "nominal", "axis": {"orient": "right", "title": "Z\u00e4hlorte"}, "field": "bez_y"}}, "selection": {"selector579": {"type": "multi", "fields": ["bez_y"]}}}], "data": {"name": "data-47fc6e758ca5d0d1778238a97b328718"}, "$schema": "https://vega.github.io/schema/vega-lite/v3.4.0.json", "datasets": {"data-47fc6e758ca5d0d1778238a97b328718": [{"knoten": "K 915", "bez_x": "Skalitzer Str. - Oberbaumstr. / K\u00f6penicker Str. - Schles. Str. (Kreuzb., 10997)", "datum": "2008-10-16T00:00:00", "zeit": "0700,1900", "art": "Pkw+Lfw,Lkw,Bus,Krad,Radf", "hour_counts_car": 2547, "hour_counts_bike": 368, "year": 2008, "Radanteil": 0.12624356775300172, "plz": "10997", "bez_y": "Skalitzer Str. - Oberbaumstr. / K\u00f6penicker Str. - Schlesische Str. (Kreuzb., 109"}, {"knoten": "K 915", "bez_x": "Skalitzer Str. - Oberbaumstr. / K\u00f6penicker Str. - Schlesische Str. (Kreuzb., 10997)", "datum": "2018-05-09T00:00:00", "zeit": "0700,1900", "art": "Pkw+Lfw,Lkw(>3.5t),Bus,Krad,Radf", "hour_counts_car": 2107, "hour_counts_bike": 894, "year": 2018, "Radanteil": 0.29790069976674444, "plz": "10997", "bez_y": "Skalitzer Str. - Oberbaumstr. / K\u00f6penicker Str. - Schlesische Str. (Kreuzb., 109"}, {"knoten": "K 2878", "bez_x": "K\u00f6penicker Stra\u00dfe / Bethaniendamm - Engeldamm    (Kreuzberg, 10997)", "datum": "2009-11-23T00:00:00", "zeit": "0700,1900", "art": "Pkw+Lfw,Lkw,Bus,Krad,Radf", "hour_counts_car": 1499, "hour_counts_bike": 188, "year": 2009, "Radanteil": 0.1114404267931239, "plz": "10997", "bez_y": "K\u00f6penicker Stra\u00dfe / Bethaniendamm - Engeldamm    (Kreuzberg, 10997)"}, {"knoten": "K 2878", "bez_x": "K\u00f6penicker Stra\u00dfe / Bethaniendamm - Engeldamm    (Kreuzberg, 10997)", "datum": "2011-10-27T00:00:00", "zeit": "0700,1900", "art": "Pkw+Lfw,Lkw,Bus,Krad,Radf", "hour_counts_car": 1535, "hour_counts_bike": 288, "year": 2011, "Radanteil": 0.15798134942402633, "plz": "10997", "bez_y": "K\u00f6penicker Stra\u00dfe / Bethaniendamm - Engeldamm    (Kreuzberg, 10997)"}, {"knoten": "K 2878", "bez_x": "K\u00f6penicker Stra\u00dfe / Bethaniendamm - Engeldamm    (Kreuzberg, 10997)", "datum": "2015-03-24T00:00:00", "zeit": "0700,1900", "art": "Pkw+Lfw,Lkw,Bus,Krad,Radf", "hour_counts_car": 1618, "hour_counts_bike": 377, "year": 2015, "Radanteil": 0.18897243107769424, "plz": "10997", "bez_y": "K\u00f6penicker Stra\u00dfe / Bethaniendamm - Engeldamm    (Kreuzberg, 10997)"}, {"knoten": "K 2878", "bez_x": "K\u00f6penicker Stra\u00dfe / Bethaniendamm - Engeldamm    (Kreuzberg, 10997)", "datum": "2018-07-11T00:00:00", "zeit": "0700,1900", "art": "Pkw+Lfw,Lkw(>3.5t),Bus,Krad,Radf", "hour_counts_car": 1442, "hour_counts_bike": 563, "year": 2018, "Radanteil": 0.28079800498753116, "plz": "10997", "bez_y": "K\u00f6penicker Stra\u00dfe / Bethaniendamm - Engeldamm    (Kreuzberg, 10997)"}, {"knoten": "Q 031209", "bez_x": "Schlesische Stra\u00dfe - Puschkinstra\u00dfe (s\u00fcdl. Am Flutgraben)   (Kreuzberg, 10997)", "datum": "2010-03-24T00:00:00", "zeit": "0600,1900", "art": "Pkw+Lfw,Lkw,Bus,Krad,Radf", "hour_counts_car": 1272, "hour_counts_bike": 258, "year": 2010, "Radanteil": 0.16862745098039217, "plz": "10997", "bez_y": "Schlesische Stra\u00dfe - Puschkinstra\u00dfe (n\u00f6rdl. Am Flutgraben)   (Kreuzberg, 10997)"}, {"knoten": "Q 031209", "bez_x": "Schlesische Stra\u00dfe - Puschkinstra\u00dfe (n\u00f6rdl. Am Flutgraben)   (Kreuzberg, 10997)", "datum": "2011-11-15T00:00:00", "zeit": "0700,1900", "art": "Pkw+Lfw,Lkw,Bus,Krad,Radf", "hour_counts_car": 1532, "hour_counts_bike": 220, "year": 2011, "Radanteil": 0.12557077625570776, "plz": "10997", "bez_y": "Schlesische Stra\u00dfe - Puschkinstra\u00dfe (n\u00f6rdl. Am Flutgraben)   (Kreuzberg, 10997)"}, {"knoten": "Q 031209", "bez_x": "Schlesische Stra\u00dfe - Puschkinstra\u00dfe (n\u00f6rdl. Am Flutgraben)   (Kreuzberg, 10997)", "datum": "2014-04-28T00:00:00", "zeit": "0700,1900", "art": "Pkw+Lfw,Lkw,Bus,Krad,Radf", "hour_counts_car": 1139, "hour_counts_bike": 396, "year": 2014, "Radanteil": 0.2579804560260586, "plz": "10997", "bez_y": "Schlesische Stra\u00dfe - Puschkinstra\u00dfe (n\u00f6rdl. Am Flutgraben)   (Kreuzberg, 10997)"}, {"knoten": "Q 031209", "bez_x": "Schlesische Stra\u00dfe - Puschkinstra\u00dfe (n\u00f6rdl. Am Flutgraben)   (Kreuzberg, 10997)", "datum": "2015-10-15T00:00:00", "zeit": "0700,1900", "art": "Pkw+Lfw,Lkw,Bus,Krad,Radf", "hour_counts_car": 1346, "hour_counts_bike": 192, "year": 2015, "Radanteil": 0.12483745123537061, "plz": "10997", "bez_y": "Schlesische Stra\u00dfe - Puschkinstra\u00dfe (n\u00f6rdl. Am Flutgraben)   (Kreuzberg, 10997)"}, {"knoten": "Q 031209", "bez_x": "Schlesische Stra\u00dfe - Puschkinstra\u00dfe (n\u00f6rdl. Am Flutgraben)   (Kreuzberg, 10997)", "datum": "2018-09-26T00:00:00", "zeit": "0700,1900", "art": "Pkw+Lfw,Lkw(>3.5t),Bus,Krad,Radf", "hour_counts_car": 982, "hour_counts_bike": 325, "year": 2018, "Radanteil": 0.2486610558530987, "plz": "10997", "bez_y": "Schlesische Stra\u00dfe - Puschkinstra\u00dfe (n\u00f6rdl. Am Flutgraben)   (Kreuzberg, 10997)"}], "data-397ee10584af86895d2bb8ae89964b56": [{"xfit": 2008.0, "yfit": 0.12624356775300072, "bez_y": "Skalitzer Str. - Oberbaumstr. / K\u00f6penicker Str. - Schlesische Str. (Kreuzb., 109"}, {"xfit": 2009.111111111111, "yfit": 0.14531658242119505, "bez_y": "Skalitzer Str. - Oberbaumstr. / K\u00f6penicker Str. - Schlesische Str. (Kreuzb., 109"}, {"xfit": 2010.2222222222222, "yfit": 0.16438959708938938, "bez_y": "Skalitzer Str. - Oberbaumstr. / K\u00f6penicker Str. - Schlesische Str. (Kreuzb., 109"}, {"xfit": 2011.3333333333333, "yfit": 0.18346261175758372, "bez_y": "Skalitzer Str. - Oberbaumstr. / K\u00f6penicker Str. - Schlesische Str. (Kreuzb., 109"}, {"xfit": 2012.4444444444443, "yfit": 0.20253562642577805, "bez_y": "Skalitzer Str. - Oberbaumstr. / K\u00f6penicker Str. - Schlesische Str. (Kreuzb., 109"}, {"xfit": 2013.5555555555557, "yfit": 0.22160864109397949, "bez_y": "Skalitzer Str. - Oberbaumstr. / K\u00f6penicker Str. - Schlesische Str. (Kreuzb., 109"}, {"xfit": 2014.6666666666667, "yfit": 0.24068165576217382, "bez_y": "Skalitzer Str. - Oberbaumstr. / K\u00f6penicker Str. - Schlesische Str. (Kreuzb., 109"}, {"xfit": 2015.7777777777778, "yfit": 0.25975467043036815, "bez_y": "Skalitzer Str. - Oberbaumstr. / K\u00f6penicker Str. - Schlesische Str. (Kreuzb., 109"}, {"xfit": 2016.888888888889, "yfit": 0.2788276850985625, "bez_y": "Skalitzer Str. - Oberbaumstr. / K\u00f6penicker Str. - Schlesische Str. (Kreuzb., 109"}, {"xfit": 2018.0, "yfit": 0.2979006997667568, "bez_y": "Skalitzer Str. - Oberbaumstr. / K\u00f6penicker Str. - Schlesische Str. (Kreuzb., 109"}, {"xfit": 2009.0, "yfit": 0.11196722601402342, "bez_y": "K\u00f6penicker Stra\u00dfe / Bethaniendamm - Engeldamm    (Kreuzberg, 10997)"}, {"xfit": 2010.0, "yfit": 0.12910389120380472, "bez_y": "K\u00f6penicker Stra\u00dfe / Bethaniendamm - Engeldamm    (Kreuzberg, 10997)"}, {"xfit": 2011.0, "yfit": 0.14624055639358602, "bez_y": "K\u00f6penicker Stra\u00dfe / Bethaniendamm - Engeldamm    (Kreuzberg, 10997)"}, {"xfit": 2012.0, "yfit": 0.16337722158336732, "bez_y": "K\u00f6penicker Stra\u00dfe / Bethaniendamm - Engeldamm    (Kreuzberg, 10997)"}, {"xfit": 2013.0, "yfit": 0.1805138867731486, "bez_y": "K\u00f6penicker Stra\u00dfe / Bethaniendamm - Engeldamm    (Kreuzberg, 10997)"}, {"xfit": 2014.0, "yfit": 0.1976505519629299, "bez_y": "K\u00f6penicker Stra\u00dfe / Bethaniendamm - Engeldamm    (Kreuzberg, 10997)"}, {"xfit": 2015.0, "yfit": 0.2147872171527112, "bez_y": "K\u00f6penicker Stra\u00dfe / Bethaniendamm - Engeldamm    (Kreuzberg, 10997)"}, {"xfit": 2016.0, "yfit": 0.2319238823424925, "bez_y": "K\u00f6penicker Stra\u00dfe / Bethaniendamm - Engeldamm    (Kreuzberg, 10997)"}, {"xfit": 2017.0, "yfit": 0.2490605475322738, "bez_y": "K\u00f6penicker Stra\u00dfe / Bethaniendamm - Engeldamm    (Kreuzberg, 10997)"}, {"xfit": 2018.0, "yfit": 0.2661972127220551, "bez_y": "K\u00f6penicker Stra\u00dfe / Bethaniendamm - Engeldamm    (Kreuzberg, 10997)"}, {"xfit": 2010.0, "yfit": 0.14681724619736514, "bez_y": "Schlesische Stra\u00dfe - Puschkinstra\u00dfe (n\u00f6rdl. Am Flutgraben)   (Kreuzberg, 10997)"}, {"xfit": 2010.888888888889, "yfit": 0.15627852814125376, "bez_y": "Schlesische Stra\u00dfe - Puschkinstra\u00dfe (n\u00f6rdl. Am Flutgraben)   (Kreuzberg, 10997)"}, {"xfit": 2011.7777777777778, "yfit": 0.16573981008514593, "bez_y": "Schlesische Stra\u00dfe - Puschkinstra\u00dfe (n\u00f6rdl. Am Flutgraben)   (Kreuzberg, 10997)"}, {"xfit": 2012.6666666666667, "yfit": 0.1752010920290381, "bez_y": "Schlesische Stra\u00dfe - Puschkinstra\u00dfe (n\u00f6rdl. Am Flutgraben)   (Kreuzberg, 10997)"}, {"xfit": 2013.5555555555557, "yfit": 0.18466237397293028, "bez_y": "Schlesische Stra\u00dfe - Puschkinstra\u00dfe (n\u00f6rdl. Am Flutgraben)   (Kreuzberg, 10997)"}, {"xfit": 2014.4444444444443, "yfit": 0.1941236559168189, "bez_y": "Schlesische Stra\u00dfe - Puschkinstra\u00dfe (n\u00f6rdl. Am Flutgraben)   (Kreuzberg, 10997)"}, {"xfit": 2015.3333333333333, "yfit": 0.20358493786071108, "bez_y": "Schlesische Stra\u00dfe - Puschkinstra\u00dfe (n\u00f6rdl. Am Flutgraben)   (Kreuzberg, 10997)"}, {"xfit": 2016.2222222222222, "yfit": 0.21304621980460325, "bez_y": "Schlesische Stra\u00dfe - Puschkinstra\u00dfe (n\u00f6rdl. Am Flutgraben)   (Kreuzberg, 10997)"}, {"xfit": 2017.111111111111, "yfit": 0.22250750174849543, "bez_y": "Schlesische Stra\u00dfe - Puschkinstra\u00dfe (n\u00f6rdl. Am Flutgraben)   (Kreuzberg, 10997)"}, {"xfit": 2018.0, "yfit": 0.2319687836923876, "bez_y": "Schlesische Stra\u00dfe - Puschkinstra\u00dfe (n\u00f6rdl. Am Flutgraben)   (Kreuzberg, 10997)"}]}}