{"config": {"view": {"width": 400, "height": 300}, "mark": {"tooltip": null}}, "data": {"name": "data-2613856a42776c7082b8bcc659024e24"}, "mark": "line", "encoding": {"color": {"type": "nominal", "field": "dir"}, "tooltip": [{"type": "quantitative", "field": "count"}, {"type": "quantitative", "field": "hour"}], "x": {"type": "quantitative", "field": "hour"}, "y": {"type": "quantitative", "field": "count"}}, "height": 200, "title": "22.04.2004: Luisenstra\u00dfe (n\u00f6rdl. Schumannstra\u00dfe)   (Mitte, 10117)", "width": 300, "$schema": "https://vega.github.io/schema/vega-lite/v3.4.0.json", "datasets": {"data-2613856a42776c7082b8bcc659024e24": [{"dir": "1->2", "hour": 0, "count": 46}, {"dir": "1->2", "hour": 1, "count": 27}, {"dir": "1->2", "hour": 2, "count": 9}, {"dir": "1->2", "hour": 3, "count": 20}, {"dir": "1->2", "hour": 4, "count": 49}, {"dir": "1->2", "hour": 5, "count": 85}, {"dir": "1->2", "hour": 6, "count": 201}, {"dir": "1->2", "hour": 7, "count": 282}, {"dir": "1->2", "hour": 8, "count": 453}, {"dir": "1->2", "hour": 9, "count": 394}, {"dir": "1->2", "hour": 10, "count": 344}, {"dir": "1->2", "hour": 11, "count": 296}, {"dir": "1->2", "hour": 12, "count": 269}, {"dir": "1->2", "hour": 13, "count": 261}, {"dir": "1->2", "hour": 14, "count": 321}, {"dir": "1->2", "hour": 15, "count": 324}, {"dir": "1->2", "hour": 16, "count": 332}, {"dir": "1->2", "hour": 17, "count": 248}, {"dir": "1->2", "hour": 18, "count": 278}, {"dir": "1->2", "hour": 19, "count": 233}, {"dir": "1->2", "hour": 20, "count": 175}, {"dir": "1->2", "hour": 21, "count": 117}, {"dir": "1->2", "hour": 22, "count": 85}, {"dir": "1->2", "hour": 23, "count": 58}, {"dir": "2->1", "hour": 0, "count": 69}, {"dir": "2->1", "hour": 1, "count": 36}, {"dir": "2->1", "hour": 2, "count": 31}, {"dir": "2->1", "hour": 3, "count": 31}, {"dir": "2->1", "hour": 4, "count": 26}, {"dir": "2->1", "hour": 5, "count": 79}, {"dir": "2->1", "hour": 6, "count": 198}, {"dir": "2->1", "hour": 7, "count": 273}, {"dir": "2->1", "hour": 8, "count": 332}, {"dir": "2->1", "hour": 9, "count": 427}, {"dir": "2->1", "hour": 10, "count": 398}, {"dir": "2->1", "hour": 11, "count": 282}, {"dir": "2->1", "hour": 12, "count": 282}, {"dir": "2->1", "hour": 13, "count": 304}, {"dir": "2->1", "hour": 14, "count": 349}, {"dir": "2->1", "hour": 15, "count": 357}, {"dir": "2->1", "hour": 16, "count": 409}, {"dir": "2->1", "hour": 17, "count": 325}, {"dir": "2->1", "hour": 18, "count": 404}, {"dir": "2->1", "hour": 19, "count": 381}, {"dir": "2->1", "hour": 20, "count": 255}, {"dir": "2->1", "hour": 21, "count": 225}, {"dir": "2->1", "hour": 22, "count": 193}, {"dir": "2->1", "hour": 23, "count": 151}]}}